mcnnm/.DS_Store
mcnnm/__init__.py
mcnnm/core.py
mcnnm/core_utils.py
mcnnm/types.py
mcnnm/utils.py
mcnnm/validation.py
mcnnm/wrappers.py
lightweight_mcnnm-1.1.4.dist-info/WHEEL
lightweight_mcnnm-1.1.4.dist-info/METADATA
lightweight_mcnnm-1.1.4.dist-info/RECORD
