Metadata-Version: 2.3
Name: lightweight-mcnnm
Version: 1.1.4
Summary: Leightweight Implementation of Athey et al. (2021)'s MC-NNM estimator
Keywords: causal,inference,panel,matrix,completion
Author: Tobias Schnabel
Author-email: Tobias Schnabel <ctobiasschnabel@gmail.com>
License: GPL-3.0
Classifier: Development Status :: 5 - Production/Stable
Classifier: License :: OSI Approved :: GNU General Public License v3 (GPLv3)
Classifier: Programming Language :: Python :: 3
Classifier: Programming Language :: Python :: 3.12
Requires-Dist: pandas>=2.0.3,<3
Requires-Dist: numpy>=2.0.1,<3
Requires-Dist: jax>=0.4.25,<0.9.0
Requires-Dist: uv~=0.9.18 ; extra == 'build'
Requires-Python: >=3.12
Project-URL: Documentation, https://mcnnm.readthedocs.io/en/latest/
Project-URL: Repository, https://github.com/tobias-schnabel/lightweight-mcnnm
Provides-Extra: build
